{
  "finess": "470019076",
  "raison_sociale": "CLINIQUE LA PALOUMERE",
  "geo": {
    "reg_code": "75",
    "reg_name": "NOUVELLE-AQUITAINE",
    "dep_code": "47",
    "dep_name": "LOT-ET-GARONNE",
    "raison_sociale": "CLINIQUE LA PALOUMERE",
    "categorie": "PSPH/EBNL"
  },
  "periodes": {
    "2025-12": {
      "02": {
        "0203": {
          "0203UA1": {
            "nb_journees_total": "33",
            "nb_journees_hc": "33",
            "nb_journees_hp": "0",
            "sexe_ratio": "0%",
            "age_moyen": "80",
            "avq_physique": "4.55",
            "avq_relationnel": "2",
            "nb_actes_csarr": "0.91"
          }
        }
      }
    }
  }
}