{
  "finess": "680001138",
  "raison_sociale": "HL DE RIBEAUVILLE",
  "geo": {
    "reg_code": "44",
    "reg_name": "GRAND EST",
    "dep_code": "68",
    "dep_name": "HAUT-RHIN",
    "raison_sociale": "HL DE RIBEAUVILLE",
    "categorie": "CH"
  },
  "periodes": {
    "2025-12": {
      "02": {
        "0203": {
          "0203LA0": {
            "nb_journees_total": "12",
            "nb_journees_hc": "0",
            "nb_journees_hp": "12",
            "sexe_ratio": "100%",
            "age_moyen": "76",
            "avq_physique": "4",
            "avq_relationnel": "2.75",
            "nb_actes_csarr": "4.5"
          },
          "0203UA2": {
            "nb_journees_total": "22",
            "nb_journees_hc": "22",
            "nb_journees_hp": "0",
            "sexe_ratio": "100%",
            "age_moyen": "79",
            "avq_physique": "8",
            "avq_relationnel": "2",
            "nb_actes_csarr": "1"
          }
        }
      }
    }
  }
}